credoai/__init__.py
credoai/_version.py
credoai/artifacts/__init__.py
credoai/artifacts/data/__init__.py
credoai/artifacts/data/base_data.py
credoai/artifacts/data/comparison_data.py
credoai/artifacts/data/tabular_data.py
credoai/artifacts/model/__init__.py
credoai/artifacts/model/base_model.py
credoai/artifacts/model/classification_model.py
credoai/artifacts/model/comparison_model.py
credoai/artifacts/model/constants_model.py
credoai/artifacts/model/regression_model.py
credoai/datasets/__init__.py
credoai/datasets/_constants.py
credoai/datasets/_fetch_censusincome.py
credoai/datasets/_fetch_credit_model.py
credoai/datasets/_fetch_creditdefault.py
credoai/datasets/_fetch_testdata.py
credoai/datasets/utils.py
credoai/datasets/static/__init__.py
credoai/datasets/static/nlp_generator_analyzer/__init__.py
credoai/datasets/static/nlp_generator_analyzer/persisted_models/__init__.py
credoai/datasets/static/nlp_generator_analyzer/persisted_models/lr_toxicity.joblib
credoai/datasets/static/nlp_generator_analyzer/prompts/__init__.py
credoai/datasets/static/nlp_generator_analyzer/prompts/bold_gender.csv
credoai/datasets/static/nlp_generator_analyzer/prompts/bold_political_ideology.csv
credoai/datasets/static/nlp_generator_analyzer/prompts/bold_profession.csv
credoai/datasets/static/nlp_generator_analyzer/prompts/bold_race.csv
credoai/datasets/static/nlp_generator_analyzer/prompts/bold_religious_ideology.csv
credoai/datasets/static/nlp_generator_analyzer/prompts/bold_religious_ideology_short.csv
credoai/datasets/static/nlp_generator_analyzer/prompts/conversationai_age.csv
credoai/datasets/static/nlp_generator_analyzer/prompts/conversationai_disability.csv
credoai/datasets/static/nlp_generator_analyzer/prompts/conversationai_gender.csv
credoai/datasets/static/nlp_generator_analyzer/prompts/conversationai_race.csv
credoai/datasets/static/nlp_generator_analyzer/prompts/conversationai_religious_ideology.csv
credoai_lens-1.1.8.dist-info/LICENSE
credoai_lens-1.1.8.dist-info/METADATA
credoai_lens-1.1.8.dist-info/WHEEL
credoai_lens-1.1.8.dist-info/top_level.txt
credoai_lens-1.1.8.dist-info/RECORD
