Metadata-Version: 2.1
Name: credoai-lens
Version: 1.1.8
Summary: Lens: comprehensive assessment framework for AI systems
Home-page: UNKNOWN
Author: Ian Eisenberg
Author-email: ian@credo.ai
Maintainer: Ian Eisenberg
Maintainer-email: ian@credo.ai
License: UNKNOWN
Download-URL: https://github.com/credo-ai/credoai_lens
Platform: UNKNOWN
Classifier: Intended Audience :: Information Technology
Classifier: Intended Audience :: Science/Research
Classifier: Programming Language :: Python :: 3.7
Classifier: Programming Language :: Python :: 3.8
Classifier: Programming Language :: Python :: 3.9
Classifier: Programming Language :: Python :: 3.10
Classifier: Topic :: Scientific/Engineering :: Artificial Intelligence
Classifier: Operating System :: OS Independent
Requires-Python: >=3.7, <3.11
Requires-Dist: credoai-connect (>=0.1.2)
Requires-Dist: fairlearn (>=0.7.0)
Requires-Dist: finsfairauditing (>=0.0.2)
Requires-Dist: lifelines (>=0.27.3)
Requires-Dist: matplotlib (>=3.0)
Requires-Dist: requests (>=2.25.1)
Requires-Dist: scikit-learn (>=0.24)
Requires-Dist: scipy (>=1.7.3)
Requires-Dist: shap (>=0.41.0)
Requires-Dist: statsmodels (>=0.13.5)
Requires-Dist: typing-extensions (>=4.3.0)
Requires-Dist: ydata-profiling (>=4.0.0)
Provides-Extra: dev
Requires-Dist: black (==22.10.0) ; extra == 'dev'
Requires-Dist: credoai-connect ; extra == 'dev'
Requires-Dist: fairlearn (==0.7.0) ; extra == 'dev'
Requires-Dist: furo (==2022.3.4) ; extra == 'dev'
Requires-Dist: ipykernel ; extra == 'dev'
Requires-Dist: lifelines (>=0.27.3) ; extra == 'dev'
Requires-Dist: nbsphinx (==0.8.7) ; extra == 'dev'
Requires-Dist: numpy (==1.23.3) ; extra == 'dev'
Requires-Dist: pandas (==1.4.4) ; extra == 'dev'
Requires-Dist: pandoc (==1.1.0) ; extra == 'dev'
Requires-Dist: prompt-toolkit (<3.0.0) ; extra == 'dev'
Requires-Dist: pydata-sphinx-theme (==0.6.3) ; extra == 'dev'
Requires-Dist: pytest-assume (>=2.4.3) ; extra == 'dev'
Requires-Dist: pytest-cov (>=3.0.0) ; extra == 'dev'
Requires-Dist: pytest-mock (>=3.8) ; extra == 'dev'
Requires-Dist: pytest-watch (>=4.2) ; extra == 'dev'
Requires-Dist: pytest (>=6.2.5) ; extra == 'dev'
Requires-Dist: responses (>=0.21.0) ; extra == 'dev'
Requires-Dist: scikit-learn (==1.1.2) ; extra == 'dev'
Requires-Dist: scipy (==1.9.1) ; extra == 'dev'
Requires-Dist: sphinx-autodoc-typehints (==1.12.0) ; extra == 'dev'
Requires-Dist: sphinx-copybutton (==0.5.0) ; extra == 'dev'
Requires-Dist: sphinx-exec-code (==0.8) ; extra == 'dev'
Requires-Dist: sphinx-fontawesome (==0.0.6) ; extra == 'dev'
Requires-Dist: sphinx-gallery (==0.10.1) ; extra == 'dev'
Requires-Dist: sphinx-rtd-theme (==1.0.0) ; extra == 'dev'
Requires-Dist: sphinx (==4.3.0) ; extra == 'dev'
Requires-Dist: tensorflow (==2.11.1) ; extra == 'dev'
Provides-Extra: full
Requires-Dist: adversarial-robustness-toolbox (>=1.10.1) ; extra == 'full'
Requires-Dist: deepchecks (>=0.9.1) ; extra == 'full'
Requires-Dist: torch (>=1.12.1) ; extra == 'full'
Requires-Dist: tensorflow (>=2.11.0) ; (sys_platform != "darwin") and extra == 'full'
Requires-Dist: tensorflow-macos (==2.10.0) ; (sys_platform == "darwin") and extra == 'full'
